{"sections":{"main":{"type":"main-page","disabled":true,"settings":{"padding_top":28,"padding_bottom":28}},"2476e48d-0f59-4750-9eac-57079797e639":{"type":"image-banner","blocks":{"template--18962054316375__2476e48d-0f59-4750-9eac-57079797e639-168423516272585926-0":{"type":"heading","settings":{"heading":"Notre laboratoire","heading_size":"h0"}},"template--18962054316375__2476e48d-0f59-4750-9eac-57079797e639-168423516272585926-1":{"type":"text","settings":{"text":"<strong>Nous sommes notre propre fabricant ce qui nous permet d'assurer la qualité de nos produits, pour vous offrir le meilleur de la nature<\/strong>","text_style":"body"}},"template--18962054316375__2476e48d-0f59-4750-9eac-57079797e639-168423516272585926-2":{"type":"buttons","disabled":true,"settings":{"button_label_1":"","button_link_1":"","button_style_secondary_1":false,"button_label_2":"","button_link_2":"","button_style_secondary_2":false}}},"block_order":["template--18962054316375__2476e48d-0f59-4750-9eac-57079797e639-168423516272585926-0","template--18962054316375__2476e48d-0f59-4750-9eac-57079797e639-168423516272585926-1","template--18962054316375__2476e48d-0f59-4750-9eac-57079797e639-168423516272585926-2"],"settings":{"image":"shopify:\/\/shop_images\/huile-pressee-froid-cbd-large-spectre.jpg","image_overlay_opacity":0,"image_height":"small","desktop_content_position":"middle-center","show_text_box":true,"desktop_content_alignment":"center","color_scheme":"background-1","image_behavior":"ambient","mobile_content_alignment":"center","stack_images_on_mobile":true,"show_text_below":true}},"93eeb6a9-0061-4caa-994f-3cb1ef0d7584":{"type":"image-with-text","blocks":{"template--18962054316375__93eeb6a9-0061-4caa-994f-3cb1ef0d7584-16842352437d7c817c-0":{"type":"heading","settings":{"heading":"SOWÉ Botanic Lab, fabricant","heading_size":"h1"}},"template--18962054316375__93eeb6a9-0061-4caa-994f-3cb1ef0d7584-16842352437d7c817c-1":{"type":"text","settings":{"text":"<p>Nous disposons de notre propre laboratoire de fabrication, incubé à la faculté des sciences de Lisbonne, dans le cadre du programme <a href=\"https:\/\/teclabs.pt\/\" target=\"_blank\" title=\"https:\/\/teclabs.pt\/\">tec labs<\/a>. Cela nous permet de contrôler la qualité, le respect de l'environnement et l'origine des produits de A à Z.<\/p><p>Chez SOWÉ, nous élaborons nos formules et développons nos produits, où les huiles sont mélangées, remplies et emballées avec précision, conformément aux directives ISO 22716 sur les bonnes pratiques de fabrication des produits cosmétiques.<\/p>","text_style":"body"}}},"block_order":["template--18962054316375__93eeb6a9-0061-4caa-994f-3cb1ef0d7584-16842352437d7c817c-0","template--18962054316375__93eeb6a9-0061-4caa-994f-3cb1ef0d7584-16842352437d7c817c-1"],"settings":{"image":"shopify:\/\/shop_images\/tec-labs-sowe.jpg","height":"small","desktop_image_width":"small","layout":"text_first","desktop_content_position":"top","desktop_content_alignment":"left","content_layout":"no-overlap","color_scheme":"background-1","image_behavior":"none","mobile_content_alignment":"left","padding_top":40,"padding_bottom":20}},"ca3647e3-869e-4e44-b240-46e42498bb91":{"type":"image-with-text","blocks":{"template--18962054316375__ca3647e3-869e-4e44-b240-46e42498bb91-16842352437d7c817c-0":{"type":"heading","settings":{"heading":"Nos fournisseurs","heading_size":"h1"}},"template--18962054316375__ca3647e3-869e-4e44-b240-46e42498bb91-16842352437d7c817c-1":{"type":"text","settings":{"text":"<p>Nos fournisseurs sont soigneusement sélectionnés pour s'assurer que nous disposons des meilleures huiles végétales possibles, 100 % biologiques et certifiées, sans OGM, vegan et pressées à froid, car nous sommes attachés à la qualité, la sécurité et la durabilité. Vous pouvez retrouver plus d'informations sur tous nos <a href=\"https:\/\/www.sowelab.com\/blogs\/ingredients\">ingrédients<\/a>.<\/p><p>Nous entretenons également une relation étroite avec nos fournisseurs afin de bien comprendre les processus d'extraction et de nous assurer que nous disposons des meilleurs ingrédients possibles, obtenus par des processus durables et équitables.<\/p>","text_style":"body"}}},"block_order":["template--18962054316375__ca3647e3-869e-4e44-b240-46e42498bb91-16842352437d7c817c-0","template--18962054316375__ca3647e3-869e-4e44-b240-46e42498bb91-16842352437d7c817c-1"],"settings":{"image":"shopify:\/\/shop_images\/huile-cbd-pressee-froid-bio-naturelle.jpg","height":"small","desktop_image_width":"medium","layout":"image_first","desktop_content_position":"top","desktop_content_alignment":"left","content_layout":"no-overlap","color_scheme":"background-1","image_behavior":"ambient","mobile_content_alignment":"left","padding_top":0,"padding_bottom":16}},"36594f9e-9956-4211-bff4-19490f11b284":{"type":"image-with-text","blocks":{"template--18962054316375__36594f9e-9956-4211-bff4-19490f11b284-16842352437d7c817c-0":{"type":"heading","settings":{"heading":"Engagement qualité","heading_size":"h1"}},"template--18962054316375__36594f9e-9956-4211-bff4-19490f11b284-16842352437d7c817c-1":{"type":"text","settings":{"text":"<p>Les produits sont testés en laboratoire afin de garantir leur stabilité et leur qualité pour chaque lot de production. Toutes nos huiles sont testées dermatologiquement, dans un laboratoire externe, pour convenir à tous les types de peau. Avec SOWÉ, gardez l'esprit tranquille, on prend soin de vous.<\/p><p>Si vous avez des questions ou besoin d'information concernant notre laboratoire et notre production, vous pouvez contacter notre Directrice R&D à l'adresse suivante : info<a href=\"mailto:alison@sowelab.com\">@sowelab.com<\/a>.<\/p>","text_style":"body"}}},"block_order":["template--18962054316375__36594f9e-9956-4211-bff4-19490f11b284-16842352437d7c817c-0","template--18962054316375__36594f9e-9956-4211-bff4-19490f11b284-16842352437d7c817c-1"],"settings":{"image":"shopify:\/\/shop_images\/ecocert-cosmos-certification-cosmetique-naturelle-qualite.jpg","height":"small","desktop_image_width":"medium","layout":"text_first","desktop_content_position":"top","desktop_content_alignment":"left","content_layout":"no-overlap","color_scheme":"background-1","image_behavior":"ambient","mobile_content_alignment":"left","padding_top":0,"padding_bottom":32}}},"order":["main","2476e48d-0f59-4750-9eac-57079797e639","93eeb6a9-0061-4caa-994f-3cb1ef0d7584","ca3647e3-869e-4e44-b240-46e42498bb91","36594f9e-9956-4211-bff4-19490f11b284"]}